setup.py
anonymized_activity_log/__init__.py
anonymized_activity_log/admin.py
anonymized_activity_log/anonymization.py
anonymized_activity_log/conf.py
anonymized_activity_log/crypto.py
anonymized_activity_log/middleware.py
anonymized_activity_log/models.py
anonymized_activity_log/router.py
anonymized_activity_log/migrations/0001_initial.py
anonymized_activity_log/migrations/0002_auto_20161031_1710.py
anonymized_activity_log/migrations/__init__.py
django_anonymized_activity_log.egg-info/PKG-INFO
django_anonymized_activity_log.egg-info/SOURCES.txt
django_anonymized_activity_log.egg-info/dependency_links.txt
django_anonymized_activity_log.egg-info/top_level.txt