Metadata-Version: 1.1
Name: django-anonymized-activity-log
Version: 0.0.19
Summary: Anonymous HTTP logging.
Home-page: https://github.com/dave-leblanc/django-anonymized-activity-log
Author: Dave LeBlanc
Author-email: iam@daveleblanc.tech
License: MIT license
Platform: UNKNOWN
Classifier: Framework :: Django
Classifier: Development Status :: 4 - Beta
Classifier: Environment :: Web Environment
Classifier: Intended Audience :: Developers
Classifier: License :: OSI Approved :: MIT License
Classifier: Programming Language :: Python
Classifier: Programming Language :: Python :: 2
Classifier: Programming Language :: Python :: 2.6
Classifier: Programming Language :: Python :: 2.7
Classifier: Programming Language :: Python :: 3.4
Classifier: Programming Language :: Python :: 3.5
Classifier: Topic :: Software Development :: Libraries :: Python Modules
